README.md
setup.cfg
setup.py
linkedin_jobs_pyscraper/__init__.py
linkedin_jobs_pyscraper/linkedin_jobs_scraper.py
linkedin_jobs_pyscraper.egg-info/PKG-INFO
linkedin_jobs_pyscraper.egg-info/SOURCES.txt
linkedin_jobs_pyscraper.egg-info/dependency_links.txt
linkedin_jobs_pyscraper.egg-info/requires.txt
linkedin_jobs_pyscraper.egg-info/top_level.txt
linkedin_jobs_pyscraper/extract/__init__.py
linkedin_jobs_pyscraper/extract/extract_job_info.py
linkedin_jobs_pyscraper/models/__init__.py
linkedin_jobs_pyscraper/models/extract/__init__.py
linkedin_jobs_pyscraper/models/extract/extractor.py
linkedin_jobs_pyscraper/models/filters/__init__.py
linkedin_jobs_pyscraper/models/filters/filters.py
linkedin_jobs_pyscraper/models/job/__init__.py
linkedin_jobs_pyscraper/models/job/job.py
linkedin_jobs_pyscraper/models/search/__init__.py
linkedin_jobs_pyscraper/models/search/searcher.py
linkedin_jobs_pyscraper/search/__init__.py
linkedin_jobs_pyscraper/search/search_jobs.py
linkedin_jobs_pyscraper/utils/__init__.py
linkedin_jobs_pyscraper/utils/helpers.py