Metadata-Version: 2.1
Name: linkedin-jobs-pyscraper
Version: 1.0.0
Summary: Scrape public jobs postings from LinkedIn in native python without selenium or any headless browser.
Home-page: https://github.com/shahrukhx01/linkedin-jobs-pyscraper
Author: Shahrukh Khan
Author-email: sk28671@gmail.com
License: UNKNOWN
Platform: UNKNOWN
Classifier: Intended Audience :: Developers
Classifier: Programming Language :: Python
Classifier: Programming Language :: Python :: 3.6
Classifier: License :: OSI Approved :: MIT License
Classifier: Operating System :: OS Independent
Requires-Python: >=3.6
